framework/__init__.py
framework/__main__.py
framework/invoke.py
framework/locate.py
http_containerize-0.4.3.dist-info/LICENSE
http_containerize-0.4.3.dist-info/METADATA
http_containerize-0.4.3.dist-info/WHEEL
http_containerize-0.4.3.dist-info/top_level.txt
http_containerize-0.4.3.dist-info/RECORD
