Metadata-Version: 2.1
Name: http-containerize
Version: 0.4.3
Summary: UNKNOWN
Home-page: https://github.com/evankanderson/pyfun
License: Apache
Platform: UNKNOWN
Classifier: Programming Language :: Python :: 3
Classifier: License :: OSI Approved :: Apache Software License
Classifier: Operating System :: Unix
Requires-Dist: cloudevents (<2,>=1.2)
Requires-Dist: Flask (<2,>=1.0.2)
